.editorconfig
.gitignore
.gitlab-ci.yml
README.rst
make_platform_deploy.sh
peek_platform_changelog.json
peek_platform_version.json
publish.settings.sh
publish.sh
pyproject.toml
.idea/modules.xml
.idea/peek-platform.iml
.idea/inspectionProfiles/Project_Default.xml
.idea/inspectionProfiles/profiles_settings.xml
peek_platform/PlatformDependencyTest.py
peek_platform/WindowsPatch.py
peek_platform/__init__.py
peek_platform/winsvc_peek_restarter.py
peek_platform.egg-info/PKG-INFO
peek_platform.egg-info/SOURCES.txt
peek_platform.egg-info/dependency_links.txt
peek_platform.egg-info/entry_points.txt
peek_platform.egg-info/requires.txt
peek_platform.egg-info/top_level.txt
peek_platform/file_config/PeekFileConfigABC.py
peek_platform/file_config/PeekFileConfigDataExchangeClientMixin.py
peek_platform/file_config/PeekFileConfigDataExchangeServerMixin.py
peek_platform/file_config/PeekFileConfigDocBuildMixin.py
peek_platform/file_config/PeekFileConfigFrontendDirMixin.py
peek_platform/file_config/PeekFileConfigHttpServerMixin.py
peek_platform/file_config/PeekFileConfigOsMixin.py
peek_platform/file_config/PeekFileConfigPlatformMixin.py
peek_platform/file_config/PeekFileConfigSqlAlchemyMixin.py
peek_platform/file_config/PeekFileConfigTest.py
peek_platform/file_config/PeekFileConfigWorkerMixin.py
peek_platform/file_config/__init__.py
peek_platform/file_config/peek_file_config_worker_task_import_mixin.py
peek_platform/platform_init/__init__.py
peek_platform/platform_init/init_platform.py
peek_platform/plugin/PluginLoaderABC.py
peek_platform/plugin/__init__.py
peek_platform/subproc_plugin_init/__init__.py
peek_platform/subproc_plugin_init/plugin_subproc_parent_main.py
peek_platform/subproc_plugin_init/plugin_subproc_parent_main_delegate.py
peek_platform/subproc_plugin_init/plugin_subproc/__init__.py
peek_platform/subproc_plugin_init/plugin_subproc/plugin_subproc_child_main.py
peek_platform/subproc_plugin_init/plugin_subproc/plugin_subproc_child_state_protocol.py
peek_platform/subproc_plugin_init/plugin_subproc/plugin_subproc_child_vortex.py
peek_platform/subproc_plugin_init/plugin_subproc/plugin_subproc_child_vortex_protocol.py
