Metadata-Version: 2.4
Name: peek-platform
Version: 5.0.4
Summary: Peek Platform - Common code that runs for Peek services
Author-email: Synerty <contact@synerty.com>
Project-URL: Homepage, https://github.com/Synerty/peek-office-service
Keywords: Peek,Python,Platform,synerty
Requires-Dist: pip>=21.0
Requires-Dist: virtualenv>=15.1.0
Requires-Dist: twine
Requires-Dist: Cython>=0.21.1
Requires-Dist: Twisted[conch,tls]
Requires-Dist: pyOpenSSL
Requires-Dist: pyasn1>=0.1.9
Requires-Dist: pyasn1-modules>=0.0.8
Requires-Dist: psycopg
Requires-Dist: psycopg-c
Requires-Dist: SQLAlchemy
Requires-Dist: alembic>=0.8.7
Requires-Dist: python-dateutil>=2.6.0
Requires-Dist: Pygments>=2.0.1
Requires-Dist: watchdog>=0.8.3
Requires-Dist: pycryptodome
Requires-Dist: cryptography
Requires-Dist: peek-plugin-base==5.0.4
Requires-Dist: peek-core-device==5.0.4
Requires-Dist: peek-core-email==5.0.4
Requires-Dist: psutil
Requires-Dist: pexpect
Requires-Dist: Shapely>=1.5.16; platform_system == "Linux"
Requires-Dist: future; platform_system == "Linux"
Requires-Dist: coverage>=4.2
Requires-Dist: mock>=2.0.0
